lammpsgenie/__init__.py
lammpsgenie/_name.py
lammpsgenie/_version.py
lammpsgenie/atoms.py
lammpsgenie/commondata.py
lammpsgenie/conftest.py
lammpsgenie/copy_ironfiles.py
lammpsgenie/mergedatafiles.py
lammpsgenie/readfiles.py
lammpsgenie/data/Fe2O3_100_down.lammps
lammpsgenie/data/Fe2O3_100_up.lammps
lammpsgenie/data/Fe2O3_50_down.lammps
lammpsgenie/data/Fe2O3_50_up.lammps
lammpsgenie-1.0.0.dist-info/LICENSE
lammpsgenie-1.0.0.dist-info/METADATA
lammpsgenie-1.0.0.dist-info/WHEEL
lammpsgenie-1.0.0.dist-info/entry_points.txt
lammpsgenie-1.0.0.dist-info/top_level.txt
lammpsgenie-1.0.0.dist-info/RECORD
