Metadata-Version: 2.1
Name: lammpsgenie
Version: 1.0.0
Summary: A package to help with LAMMPS data and dump files.
Home-page: https://github.com/RuiApostolo/lmpdtmrg
Author: Rui Apóstolo
Author-email: ruiapostolo+lammpsgenie@gmail.com
Project-URL: Bug Tracker, https://github.com/RuiApostolo/lammpsgenie/issues
Classifier: Development Status :: 5 - Production/Stable
Classifier: Intended Audience :: Science/Research
Classifier: License :: OSI Approved
Classifier: License :: OSI Approved :: GNU General Public License v3 (GPLv3)
Classifier: Operating System :: Unix
Classifier: Programming Language :: Python :: 3
Classifier: Topic :: Scientific/Engineering
Classifier: Topic :: Scientific/Engineering :: Chemistry
Classifier: Topic :: Scientific/Engineering :: Physics
Requires-Python: >=3.6
License-File: LICENSE
Requires-Dist: PyYAML (>=5.3.1)
